<annotation>
	<folder>images</folder>
	<filename>image019.jpg</filename>
	<path>C:\Users\krx\Pictures\ML Training Data\igomaschine_small\train\images\image019.jpg</path>
	<source>
		<database>Unknown</database>
	</source>
	<size>
		<width>340</width>
		<height>255</height>
		<depth>3</depth>
	</size>
	<segmented>0</segmented>
	<object>
		<name>crossing</name>
		<pose>Unspecified</pose>
		<truncated>0</truncated>
		<difficult>0</difficult>
		<bndbox>
			<xmin>26</xmin>
			<ymin>120</ymin>
			<xmax>48</xmax>
			<ymax>140</ymax>
		</bndbox>
	</object>
	<object>
		<name>crossing</name>
		<pose>Unspecified</pose>
		<truncated>0</truncated>
		<difficult>0</difficult>
		<bndbox>
			<xmin>68</xmin>
			<ymin>111</ymin>
			<xmax>84</xmax>
			<ymax>129</ymax>
		</bndbox>
	</object>
	<object>
		<name>crossing</name>
		<pose>Unspecified</pose>
		<truncated>0</truncated>
		<difficult>0</difficult>
		<bndbox>
			<xmin>274</xmin>
			<ymin>55</ymin>
			<xmax>292</xmax>
			<ymax>73</ymax>
		</bndbox>
	</object>
	<object>
		<name>crossing</name>
		<pose>Unspecified</pose>
		<truncated>0</truncated>
		<difficult>0</difficult>
		<bndbox>
			<xmin>83</xmin>
			<ymin>177</ymin>
			<xmax>107</xmax>
			<ymax>196</ymax>
		</bndbox>
	</object>
	<object>
		<name>white</name>
		<pose>Unspecified</pose>
		<truncated>0</truncated>
		<difficult>0</difficult>
		<bndbox>
			<xmin>114</xmin>
			<ymin>119</ymin>
			<xmax>156</xmax>
			<ymax>157</ymax>
		</bndbox>
	</object>
	<object>
		<name>white</name>
		<pose>Unspecified</pose>
		<truncated>0</truncated>
		<difficult>0</difficult>
		<bndbox>
			<xmin>72</xmin>
			<ymin>44</ymin>
			<xmax>110</xmax>
			<ymax>71</ymax>
		</bndbox>
	</object>
	<object>
		<name>white</name>
		<pose>Unspecified</pose>
		<truncated>0</truncated>
		<difficult>0</difficult>
		<bndbox>
			<xmin>154</xmin>
			<ymin>47</ymin>
			<xmax>189</xmax>
			<ymax>74</ymax>
		</bndbox>
	</object>
	<object>
		<name>white</name>
		<pose>Unspecified</pose>
		<truncated>0</truncated>
		<difficult>0</difficult>
		<bndbox>
			<xmin>243</xmin>
			<ymin>78</ymin>
			<xmax>282</xmax>
			<ymax>109</ymax>
		</bndbox>
	</object>
	<object>
		<name>white</name>
		<pose>Unspecified</pose>
		<truncated>0</truncated>
		<difficult>0</difficult>
		<bndbox>
			<xmin>251</xmin>
			<ymin>150</ymin>
			<xmax>295</xmax>
			<ymax>188</ymax>
		</bndbox>
	</object>
	<object>
		<name>black</name>
		<pose>Unspecified</pose>
		<truncated>0</truncated>
		<difficult>0</difficult>
		<bndbox>
			<xmin>126</xmin>
			<ymin>83</ymin>
			<xmax>163</xmax>
			<ymax>117</ymax>
		</bndbox>
	</object>
	<object>
		<name>black</name>
		<pose>Unspecified</pose>
		<truncated>0</truncated>
		<difficult>0</difficult>
		<bndbox>
			<xmin>108</xmin>
			<ymin>36</ymin>
			<xmax>142</xmax>
			<ymax>63</ymax>
		</bndbox>
	</object>
	<object>
		<name>black</name>
		<pose>Unspecified</pose>
		<truncated>0</truncated>
		<difficult>0</difficult>
		<bndbox>
			<xmin>66</xmin>
			<ymin>19</ymin>
			<xmax>100</xmax>
			<ymax>44</ymax>
		</bndbox>
	</object>
	<object>
		<name>black</name>
		<pose>Unspecified</pose>
		<truncated>0</truncated>
		<difficult>0</difficult>
		<bndbox>
			<xmin>246</xmin>
			<ymin>25</ymin>
			<xmax>280</xmax>
			<ymax>51</ymax>
		</bndbox>
	</object>
	<object>
		<name>black</name>
		<pose>Unspecified</pose>
		<truncated>0</truncated>
		<difficult>0</difficult>
		<bndbox>
			<xmin>194</xmin>
			<ymin>128</ymin>
			<xmax>234</xmax>
			<ymax>163</ymax>
		</bndbox>
	</object>
</annotation>
