<annotation>
	<folder>images</folder>
	<filename>image007.jpg</filename>
	<path>C:\Users\krx\Pictures\ML Training Data\igomaschine_small\train\images\image007.jpg</path>
	<source>
		<database>Unknown</database>
	</source>
	<size>
		<width>340</width>
		<height>226</height>
		<depth>3</depth>
	</size>
	<segmented>0</segmented>
	<object>
		<name>black</name>
		<pose>Unspecified</pose>
		<truncated>0</truncated>
		<difficult>0</difficult>
		<bndbox>
			<xmin>131</xmin>
			<ymin>63</ymin>
			<xmax>191</xmax>
			<ymax>96</ymax>
		</bndbox>
	</object>
	<object>
		<name>black</name>
		<pose>Unspecified</pose>
		<truncated>0</truncated>
		<difficult>0</difficult>
		<bndbox>
			<xmin>273</xmin>
			<ymin>6</ymin>
			<xmax>314</xmax>
			<ymax>28</ymax>
		</bndbox>
	</object>
	<object>
		<name>black</name>
		<pose>Unspecified</pose>
		<truncated>0</truncated>
		<difficult>0</difficult>
		<bndbox>
			<xmin>55</xmin>
			<ymin>93</ymin>
			<xmax>123</xmax>
			<ymax>128</ymax>
		</bndbox>
	</object>
	<object>
		<name>black</name>
		<pose>Unspecified</pose>
		<truncated>0</truncated>
		<difficult>0</difficult>
		<bndbox>
			<xmin>115</xmin>
			<ymin>107</ymin>
			<xmax>189</xmax>
			<ymax>146</ymax>
		</bndbox>
	</object>
	<object>
		<name>black</name>
		<pose>Unspecified</pose>
		<truncated>0</truncated>
		<difficult>0</difficult>
		<bndbox>
			<xmin>218</xmin>
			<ymin>160</ymin>
			<xmax>308</xmax>
			<ymax>209</ymax>
		</bndbox>
	</object>
	<object>
		<name>crossing</name>
		<pose>Unspecified</pose>
		<truncated>0</truncated>
		<difficult>0</difficult>
		<bndbox>
			<xmin>300</xmin>
			<ymin>132</ymin>
			<xmax>322</xmax>
			<ymax>153</ymax>
		</bndbox>
	</object>
	<object>
		<name>crossing</name>
		<pose>Unspecified</pose>
		<truncated>0</truncated>
		<difficult>0</difficult>
		<bndbox>
			<xmin>231</xmin>
			<ymin>121</ymin>
			<xmax>258</xmax>
			<ymax>139</ymax>
		</bndbox>
	</object>
	<object>
		<name>crossing</name>
		<pose>Unspecified</pose>
		<truncated>0</truncated>
		<difficult>0</difficult>
		<bndbox>
			<xmin>36</xmin>
			<ymin>190</ymin>
			<xmax>60</xmax>
			<ymax>206</ymax>
		</bndbox>
	</object>
	<object>
		<name>white</name>
		<pose>Unspecified</pose>
		<truncated>0</truncated>
		<difficult>0</difficult>
		<bndbox>
			<xmin>59</xmin>
			<ymin>126</ymin>
			<xmax>139</xmax>
			<ymax>171</ymax>
		</bndbox>
	</object>
	<object>
		<name>white</name>
		<pose>Unspecified</pose>
		<truncated>0</truncated>
		<difficult>0</difficult>
		<bndbox>
			<xmin>193</xmin>
			<ymin>38</ymin>
			<xmax>247</xmax>
			<ymax>68</ymax>
		</bndbox>
	</object>
	<object>
		<name>white</name>
		<pose>Unspecified</pose>
		<truncated>0</truncated>
		<difficult>0</difficult>
		<bndbox>
			<xmin>239</xmin>
			<ymin>19</ymin>
			<xmax>289</xmax>
			<ymax>45</ymax>
		</bndbox>
	</object>
	<object>
		<name>white</name>
		<pose>Unspecified</pose>
		<truncated>1</truncated>
		<difficult>0</difficult>
		<bndbox>
			<xmin>1</xmin>
			<ymin>84</ymin>
			<xmax>67</xmax>
			<ymax>118</ymax>
		</bndbox>
	</object>
	<object>
		<name>white</name>
		<pose>Unspecified</pose>
		<truncated>0</truncated>
		<difficult>0</difficult>
		<bndbox>
			<xmin>74</xmin>
			<ymin>173</ymin>
			<xmax>171</xmax>
			<ymax>225</ymax>
		</bndbox>
	</object>
	<object>
		<name>crossing</name>
		<pose>Unspecified</pose>
		<truncated>0</truncated>
		<difficult>0</difficult>
		<bndbox>
			<xmin>287</xmin>
			<ymin>84</ymin>
			<xmax>307</xmax>
			<ymax>100</ymax>
		</bndbox>
	</object>
</annotation>
