<annotation>
	<folder>images</folder>
	<filename>image016.jpg</filename>
	<path>C:\Users\krx\Pictures\ML Training Data\igomaschine_small\train\images\image016.jpg</path>
	<source>
		<database>Unknown</database>
	</source>
	<size>
		<width>340</width>
		<height>191</height>
		<depth>3</depth>
	</size>
	<segmented>0</segmented>
	<object>
		<name>white</name>
		<pose>Unspecified</pose>
		<truncated>0</truncated>
		<difficult>0</difficult>
		<bndbox>
			<xmin>76</xmin>
			<ymin>71</ymin>
			<xmax>135</xmax>
			<ymax>102</ymax>
		</bndbox>
	</object>
	<object>
		<name>white</name>
		<pose>Unspecified</pose>
		<truncated>0</truncated>
		<difficult>0</difficult>
		<bndbox>
			<xmin>119</xmin>
			<ymin>86</ymin>
			<xmax>195</xmax>
			<ymax>130</ymax>
		</bndbox>
	</object>
	<object>
		<name>white</name>
		<pose>Unspecified</pose>
		<truncated>0</truncated>
		<difficult>0</difficult>
		<bndbox>
			<xmin>195</xmin>
			<ymin>71</ymin>
			<xmax>258</xmax>
			<ymax>99</ymax>
		</bndbox>
	</object>
	<object>
		<name>white</name>
		<pose>Unspecified</pose>
		<truncated>1</truncated>
		<difficult>0</difficult>
		<bndbox>
			<xmin>1</xmin>
			<ymin>83</ymin>
			<xmax>53</xmax>
			<ymax>121</ymax>
		</bndbox>
	</object>
	<object>
		<name>black</name>
		<pose>Unspecified</pose>
		<truncated>0</truncated>
		<difficult>0</difficult>
		<bndbox>
			<xmin>100</xmin>
			<ymin>51</ymin>
			<xmax>132</xmax>
			<ymax>68</ymax>
		</bndbox>
	</object>
	<object>
		<name>black</name>
		<pose>Unspecified</pose>
		<truncated>0</truncated>
		<difficult>0</difficult>
		<bndbox>
			<xmin>204</xmin>
			<ymin>53</ymin>
			<xmax>245</xmax>
			<ymax>74</ymax>
		</bndbox>
	</object>
	<object>
		<name>black</name>
		<pose>Unspecified</pose>
		<truncated>0</truncated>
		<difficult>0</difficult>
		<bndbox>
			<xmin>201</xmin>
			<ymin>84</ymin>
			<xmax>284</xmax>
			<ymax>131</ymax>
		</bndbox>
	</object>
	<object>
		<name>black</name>
		<pose>Unspecified</pose>
		<truncated>0</truncated>
		<difficult>0</difficult>
		<bndbox>
			<xmin>256</xmin>
			<ymin>68</ymin>
			<xmax>322</xmax>
			<ymax>105</ymax>
		</bndbox>
	</object>
	<object>
		<name>black</name>
		<pose>Unspecified</pose>
		<truncated>0</truncated>
		<difficult>0</difficult>
		<bndbox>
			<xmin>19</xmin>
			<ymin>55</ymin>
			<xmax>58</xmax>
			<ymax>76</ymax>
		</bndbox>
	</object>
	<object>
		<name>crossing</name>
		<pose>Unspecified</pose>
		<truncated>0</truncated>
		<difficult>0</difficult>
		<bndbox>
			<xmin>125</xmin>
			<ymin>147</ymin>
			<xmax>152</xmax>
			<ymax>170</ymax>
		</bndbox>
	</object>
	<object>
		<name>crossing</name>
		<pose>Unspecified</pose>
		<truncated>0</truncated>
		<difficult>0</difficult>
		<bndbox>
			<xmin>227</xmin>
			<ymin>153</ymin>
			<xmax>254</xmax>
			<ymax>177</ymax>
		</bndbox>
	</object>
	<object>
		<name>crossing</name>
		<pose>Unspecified</pose>
		<truncated>0</truncated>
		<difficult>0</difficult>
		<bndbox>
			<xmin>304</xmin>
			<ymin>114</ymin>
			<xmax>330</xmax>
			<ymax>139</ymax>
		</bndbox>
	</object>
</annotation>
